{
  "animateLoading": true,
  "borderRadius": "{{appsmith.theme.borderRadius.appBorderRadius}}",
  "bottomRow": 5,
  "boxShadow": "none",
  "buttonColor": "{{appsmith.theme.colors.primaryColor}}",
  "buttonVariant": "PRIMARY",
  "dynamicBindingPathList": [
    {
      "key": "buttonColor"
    },
    {
      "key": "borderRadius"
    }
  ],
  "dynamicTriggerPathList": [],
  "iconName": "log-out",
  "isDisabled": false,
  "isLoading": false,
  "isVisible": true,
  "key": "8qyi0wqjwa",
  "leftColumn": 59,
  "minWidth": 50,
  "mobileBottomRow": 5,
  "mobileLeftColumn": 59,
  "mobileRightColumn": 63,
  "mobileTopRow": 1,
  "needsErrorInfo": false,
  "parentColumnSpace": 10.9736328125,
  "parentId": "1r82sdzzav",
  "parentRowSpace": 10,
  "renderMode": "CANVAS",
  "responsiveBehavior": "hug",
  "rightColumn": 63,
  "topRow": 1,
  "type": "ICON_BUTTON_WIDGET",
  "version": 1,
  "widgetId": "n6mx6fzwej",
  "widgetName": "btn_logout"
}